uas_standards/__init__.py
uas_standards/_version.py
uas_standards/ansi_cta_2063_a.py
uas_standards/en4709_02.py
uas_standards/eurocae_ed269.py
uas_standards/eurocae_ed318.py
uas_standards/astm/__init__.py
uas_standards/astm/f3411/__init__.py
uas_standards/astm/f3411/v19/__init__.py
uas_standards/astm/f3411/v19/api.py
uas_standards/astm/f3411/v19/constants.py
uas_standards/astm/f3411/v22a/__init__.py
uas_standards/astm/f3411/v22a/api.py
uas_standards/astm/f3411/v22a/constants.py
uas_standards/astm/f3548/__init__.py
uas_standards/astm/f3548/v21/__init__.py
uas_standards/astm/f3548/v21/api.py
uas_standards/astm/f3548/v21/constants.py
uas_standards/interuss/__init__.py
uas_standards/interuss/automated_testing/__init__.py
uas_standards/interuss/automated_testing/flight_planning/__init__.py
uas_standards/interuss/automated_testing/flight_planning/v1/__init__.py
uas_standards/interuss/automated_testing/flight_planning/v1/api.py
uas_standards/interuss/automated_testing/flight_planning/v1/constants.py
uas_standards/interuss/automated_testing/geo_awareness/__init__.py
uas_standards/interuss/automated_testing/geo_awareness/v1/__init__.py
uas_standards/interuss/automated_testing/geo_awareness/v1/api.py
uas_standards/interuss/automated_testing/geo_awareness/v1/constants.py
uas_standards/interuss/automated_testing/geospatial_map/__init__.py
uas_standards/interuss/automated_testing/geospatial_map/v1/__init__.py
uas_standards/interuss/automated_testing/geospatial_map/v1/api.py
uas_standards/interuss/automated_testing/geospatial_map/v1/constants.py
uas_standards/interuss/automated_testing/rid/__init__.py
uas_standards/interuss/automated_testing/rid/v1/__init__.py
uas_standards/interuss/automated_testing/rid/v1/constants.py
uas_standards/interuss/automated_testing/rid/v1/injection.py
uas_standards/interuss/automated_testing/rid/v1/observation.py
uas_standards/interuss/automated_testing/scd/__init__.py
uas_standards/interuss/automated_testing/scd/v1/__init__.py
uas_standards-4.1.1.dist-info/licenses/LICENSE.md
uas_standards-4.1.1.dist-info/METADATA
uas_standards-4.1.1.dist-info/WHEEL
uas_standards-4.1.1.dist-info/top_level.txt
uas_standards-4.1.1.dist-info/RECORD
