Metadata-Version: 2.4
Name: uas_standards
Version: 4.1.1
Summary: Data types and tools for working with standards related to uncrewed aircraft systems (UAS)
Author-email: InterUSS Platform <tsc@lists.interussplatform.org>
License-Expression: Apache-2.0
Project-URL: Homepage, https://github.com/interuss/uas_standards
Project-URL: Bug Tracker, https://github.com/interuss/uas_standards/issues
Classifier: Programming Language :: Python :: 3
Classifier: Operating System :: OS Independent
Requires-Python: >=3.10
License-File: LICENSE.md
Requires-Dist: implicitdict>=4.0.1
Dynamic: license-file
